{
	"textures": [
		{
			"image": "28.png",
			"format": "RGBA8888",
			"size": {
				"w": 664,
				"h": 94
			},
			"scale": 1,
			"frames": [
				{
					"filename": "1",
					"rotated": false,
					"trimmed": false,
					"sourceSize": {
						"w": 164,
						"h": 92
					},
					"spriteSourceSize": {
						"x": 0,
						"y": 0,
						"w": 164,
						"h": 92
					},
					"frame": {
						"x": 1,
						"y": 1,
						"w": 164,
						"h": 92
					}
				},
				{
					"filename": "2",
					"rotated": false,
					"trimmed": false,
					"sourceSize": {
						"w": 164,
						"h": 92
					},
					"spriteSourceSize": {
						"x": 0,
						"y": 0,
						"w": 164,
						"h": 92
					},
					"frame": {
						"x": 167,
						"y": 1,
						"w": 164,
						"h": 92
					}
				},
				{
					"filename": "3",
					"rotated": false,
					"trimmed": false,
					"sourceSize": {
						"w": 164,
						"h": 92
					},
					"spriteSourceSize": {
						"x": 0,
						"y": 0,
						"w": 164,
						"h": 92
					},
					"frame": {
						"x": 167,
						"y": 1,
						"w": 164,
						"h": 92
					}
				},
				{
					"filename": "4",
					"rotated": false,
					"trimmed": false,
					"sourceSize": {
						"w": 164,
						"h": 92
					},
					"spriteSourceSize": {
						"x": 0,
						"y": 0,
						"w": 164,
						"h": 92
					},
					"frame": {
						"x": 167,
						"y": 1,
						"w": 164,
						"h": 92
					}
				},
				{
					"filename": "5",
					"rotated": false,
					"trimmed": false,
					"sourceSize": {
						"w": 164,
						"h": 92
					},
					"spriteSourceSize": {
						"x": 0,
						"y": 0,
						"w": 164,
						"h": 92
					},
					"frame": {
						"x": 333,
						"y": 1,
						"w": 164,
						"h": 92
					}
				},
				{
					"filename": "6",
					"rotated": false,
					"trimmed": false,
					"sourceSize": {
						"w": 164,
						"h": 92
					},
					"spriteSourceSize": {
						"x": 0,
						"y": 0,
						"w": 164,
						"h": 92
					},
					"frame": {
						"x": 499,
						"y": 1,
						"w": 164,
						"h": 92
					}
				}
			]
		}
	],
	"meta": {
		"app": "https://www.codeandweb.com/texturepacker",
		"version": "3.0",
		"smartupdate": "$TexturePacker:SmartUpdate:ae23a858425e5cb89bae1a251a4d7d03:a6b91bd417e68a78ab0989ff2872af2c:6744f97c412c9deae107ede250fa8def$"
	}
}
