{
	"textures": [
		{
			"image": "14.png",
			"format": "RGBA8888",
			"size": {
				"w": 220,
				"h": 58
			},
			"scale": 1,
			"frames": [
				{
					"filename": "1",
					"rotated": false,
					"trimmed": false,
					"sourceSize": {
						"w": 53,
						"h": 56
					},
					"spriteSourceSize": {
						"x": 0,
						"y": 0,
						"w": 53,
						"h": 56
					},
					"frame": {
						"x": 1,
						"y": 1,
						"w": 53,
						"h": 56
					}
				},
				{
					"filename": "2",
					"rotated": false,
					"trimmed": false,
					"sourceSize": {
						"w": 53,
						"h": 56
					},
					"spriteSourceSize": {
						"x": 0,
						"y": 0,
						"w": 53,
						"h": 56
					},
					"frame": {
						"x": 1,
						"y": 1,
						"w": 53,
						"h": 56
					}
				},
				{
					"filename": "3",
					"rotated": false,
					"trimmed": false,
					"sourceSize": {
						"w": 53,
						"h": 56
					},
					"spriteSourceSize": {
						"x": 0,
						"y": 0,
						"w": 53,
						"h": 56
					},
					"frame": {
						"x": 1,
						"y": 1,
						"w": 53,
						"h": 56
					}
				},
				{
					"filename": "4",
					"rotated": false,
					"trimmed": false,
					"sourceSize": {
						"w": 53,
						"h": 56
					},
					"spriteSourceSize": {
						"x": 0,
						"y": 0,
						"w": 53,
						"h": 56
					},
					"frame": {
						"x": 1,
						"y": 1,
						"w": 53,
						"h": 56
					}
				},
				{
					"filename": "5",
					"rotated": false,
					"trimmed": false,
					"sourceSize": {
						"w": 53,
						"h": 56
					},
					"spriteSourceSize": {
						"x": 0,
						"y": 0,
						"w": 53,
						"h": 56
					},
					"frame": {
						"x": 1,
						"y": 1,
						"w": 53,
						"h": 56
					}
				},
				{
					"filename": "6",
					"rotated": false,
					"trimmed": false,
					"sourceSize": {
						"w": 53,
						"h": 56
					},
					"spriteSourceSize": {
						"x": 0,
						"y": 0,
						"w": 53,
						"h": 56
					},
					"frame": {
						"x": 56,
						"y": 1,
						"w": 53,
						"h": 56
					}
				},
				{
					"filename": "7",
					"rotated": false,
					"trimmed": false,
					"sourceSize": {
						"w": 53,
						"h": 56
					},
					"spriteSourceSize": {
						"x": 0,
						"y": 0,
						"w": 53,
						"h": 56
					},
					"frame": {
						"x": 111,
						"y": 1,
						"w": 53,
						"h": 56
					}
				},
				{
					"filename": "8",
					"rotated": false,
					"trimmed": false,
					"sourceSize": {
						"w": 53,
						"h": 56
					},
					"spriteSourceSize": {
						"x": 0,
						"y": 0,
						"w": 53,
						"h": 56
					},
					"frame": {
						"x": 166,
						"y": 1,
						"w": 53,
						"h": 56
					}
				}
			]
		}
	],
	"meta": {
		"app": "https://www.codeandweb.com/texturepacker",
		"version": "3.0",
		"smartupdate": "$TexturePacker:SmartUpdate:33d4b8633779ea8b1fe49db547dd0cbb:4f0298eae69fdfacad3d3767496dbf58:314981a747ce268771bc8e79b7e50fdf$"
	}
}
