{
	"textures": [
		{
			"image": "9.png",
			"format": "RGBA8888",
			"size": {
				"w": 416,
				"h": 97
			},
			"scale": 1,
			"frames": [
				{
					"filename": "1",
					"rotated": false,
					"trimmed": false,
					"sourceSize": {
						"w": 102,
						"h": 95
					},
					"spriteSourceSize": {
						"x": 0,
						"y": 0,
						"w": 102,
						"h": 95
					},
					"frame": {
						"x": 1,
						"y": 1,
						"w": 102,
						"h": 95
					}
				},
				{
					"filename": "2",
					"rotated": false,
					"trimmed": false,
					"sourceSize": {
						"w": 102,
						"h": 95
					},
					"spriteSourceSize": {
						"x": 0,
						"y": 0,
						"w": 102,
						"h": 95
					},
					"frame": {
						"x": 1,
						"y": 1,
						"w": 102,
						"h": 95
					}
				},
				{
					"filename": "3",
					"rotated": false,
					"trimmed": false,
					"sourceSize": {
						"w": 102,
						"h": 95
					},
					"spriteSourceSize": {
						"x": 0,
						"y": 0,
						"w": 102,
						"h": 95
					},
					"frame": {
						"x": 1,
						"y": 1,
						"w": 102,
						"h": 95
					}
				},
				{
					"filename": "4",
					"rotated": false,
					"trimmed": false,
					"sourceSize": {
						"w": 102,
						"h": 95
					},
					"spriteSourceSize": {
						"x": 0,
						"y": 0,
						"w": 102,
						"h": 95
					},
					"frame": {
						"x": 105,
						"y": 1,
						"w": 102,
						"h": 95
					}
				},
				{
					"filename": "5",
					"rotated": false,
					"trimmed": false,
					"sourceSize": {
						"w": 102,
						"h": 95
					},
					"spriteSourceSize": {
						"x": 0,
						"y": 0,
						"w": 102,
						"h": 95
					},
					"frame": {
						"x": 209,
						"y": 1,
						"w": 102,
						"h": 95
					}
				},
				{
					"filename": "6",
					"rotated": false,
					"trimmed": false,
					"sourceSize": {
						"w": 102,
						"h": 95
					},
					"spriteSourceSize": {
						"x": 0,
						"y": 0,
						"w": 102,
						"h": 95
					},
					"frame": {
						"x": 313,
						"y": 1,
						"w": 102,
						"h": 95
					}
				}
			]
		}
	],
	"meta": {
		"app": "https://www.codeandweb.com/texturepacker",
		"version": "3.0",
		"smartupdate": "$TexturePacker:SmartUpdate:fd43c0ef46e29c531be99f03a5653eda:098dc31abf1c3baf875512280b391acd:005cfeeecdb881bde464c140babce266$"
	}
}
