{
	"textures": [
		{
			"image": "27.png",
			"format": "RGBA8888",
			"size": {
				"w": 392,
				"h": 237
			},
			"scale": 1,
			"frames": [
				{
					"filename": "1",
					"rotated": false,
					"trimmed": false,
					"sourceSize": {
						"w": 194,
						"h": 77
					},
					"spriteSourceSize": {
						"x": 0,
						"y": 0,
						"w": 194,
						"h": 77
					},
					"frame": {
						"x": 1,
						"y": 1,
						"w": 194,
						"h": 77
					}
				},
				{
					"filename": "10",
					"rotated": false,
					"trimmed": false,
					"sourceSize": {
						"w": 194,
						"h": 77
					},
					"spriteSourceSize": {
						"x": 0,
						"y": 0,
						"w": 194,
						"h": 77
					},
					"frame": {
						"x": 1,
						"y": 80,
						"w": 194,
						"h": 77
					}
				},
				{
					"filename": "11",
					"rotated": false,
					"trimmed": false,
					"sourceSize": {
						"w": 194,
						"h": 77
					},
					"spriteSourceSize": {
						"x": 0,
						"y": 0,
						"w": 194,
						"h": 77
					},
					"frame": {
						"x": 1,
						"y": 159,
						"w": 194,
						"h": 77
					}
				},
				{
					"filename": "2",
					"rotated": false,
					"trimmed": false,
					"sourceSize": {
						"w": 194,
						"h": 77
					},
					"spriteSourceSize": {
						"x": 0,
						"y": 0,
						"w": 194,
						"h": 77
					},
					"frame": {
						"x": 197,
						"y": 1,
						"w": 194,
						"h": 77
					}
				},
				{
					"filename": "3",
					"rotated": false,
					"trimmed": false,
					"sourceSize": {
						"w": 194,
						"h": 77
					},
					"spriteSourceSize": {
						"x": 0,
						"y": 0,
						"w": 194,
						"h": 77
					},
					"frame": {
						"x": 197,
						"y": 1,
						"w": 194,
						"h": 77
					}
				},
				{
					"filename": "4",
					"rotated": false,
					"trimmed": false,
					"sourceSize": {
						"w": 194,
						"h": 77
					},
					"spriteSourceSize": {
						"x": 0,
						"y": 0,
						"w": 194,
						"h": 77
					},
					"frame": {
						"x": 197,
						"y": 1,
						"w": 194,
						"h": 77
					}
				},
				{
					"filename": "5",
					"rotated": false,
					"trimmed": false,
					"sourceSize": {
						"w": 194,
						"h": 77
					},
					"spriteSourceSize": {
						"x": 0,
						"y": 0,
						"w": 194,
						"h": 77
					},
					"frame": {
						"x": 197,
						"y": 80,
						"w": 194,
						"h": 77
					}
				},
				{
					"filename": "6",
					"rotated": false,
					"trimmed": false,
					"sourceSize": {
						"w": 194,
						"h": 77
					},
					"spriteSourceSize": {
						"x": 0,
						"y": 0,
						"w": 194,
						"h": 77
					},
					"frame": {
						"x": 197,
						"y": 159,
						"w": 194,
						"h": 77
					}
				},
				{
					"filename": "7",
					"rotated": false,
					"trimmed": false,
					"sourceSize": {
						"w": 194,
						"h": 77
					},
					"spriteSourceSize": {
						"x": 0,
						"y": 0,
						"w": 194,
						"h": 77
					},
					"frame": {
						"x": 197,
						"y": 159,
						"w": 194,
						"h": 77
					}
				},
				{
					"filename": "8",
					"rotated": false,
					"trimmed": false,
					"sourceSize": {
						"w": 194,
						"h": 77
					},
					"spriteSourceSize": {
						"x": 0,
						"y": 0,
						"w": 194,
						"h": 77
					},
					"frame": {
						"x": 197,
						"y": 159,
						"w": 194,
						"h": 77
					}
				},
				{
					"filename": "9",
					"rotated": false,
					"trimmed": false,
					"sourceSize": {
						"w": 194,
						"h": 77
					},
					"spriteSourceSize": {
						"x": 0,
						"y": 0,
						"w": 194,
						"h": 77
					},
					"frame": {
						"x": 197,
						"y": 159,
						"w": 194,
						"h": 77
					}
				}
			]
		}
	],
	"meta": {
		"app": "https://www.codeandweb.com/texturepacker",
		"version": "3.0",
		"smartupdate": "$TexturePacker:SmartUpdate:2defede4dde8729a0e5d7cc7a4b39dac:3e84722d2c89f1919a742a4452b5509c:836cc10e56153e419e3eea5c3424eb02$"
	}
}
