{
	"textures": [
		{
			"image": "25.png",
			"format": "RGBA8888",
			"size": {
				"w": 282,
				"h": 45
			},
			"scale": 1,
			"frames": [
				{
					"filename": "1",
					"rotated": false,
					"trimmed": false,
					"sourceSize": {
						"w": 92,
						"h": 43
					},
					"spriteSourceSize": {
						"x": 0,
						"y": 0,
						"w": 92,
						"h": 43
					},
					"frame": {
						"x": 1,
						"y": 1,
						"w": 92,
						"h": 43
					}
				},
				{
					"filename": "2",
					"rotated": false,
					"trimmed": false,
					"sourceSize": {
						"w": 92,
						"h": 43
					},
					"spriteSourceSize": {
						"x": 0,
						"y": 0,
						"w": 92,
						"h": 43
					},
					"frame": {
						"x": 1,
						"y": 1,
						"w": 92,
						"h": 43
					}
				},
				{
					"filename": "3",
					"rotated": false,
					"trimmed": false,
					"sourceSize": {
						"w": 92,
						"h": 43
					},
					"spriteSourceSize": {
						"x": 0,
						"y": 0,
						"w": 92,
						"h": 43
					},
					"frame": {
						"x": 1,
						"y": 1,
						"w": 92,
						"h": 43
					}
				},
				{
					"filename": "4",
					"rotated": false,
					"trimmed": false,
					"sourceSize": {
						"w": 92,
						"h": 43
					},
					"spriteSourceSize": {
						"x": 0,
						"y": 0,
						"w": 92,
						"h": 43
					},
					"frame": {
						"x": 1,
						"y": 1,
						"w": 92,
						"h": 43
					}
				},
				{
					"filename": "5",
					"rotated": false,
					"trimmed": false,
					"sourceSize": {
						"w": 92,
						"h": 43
					},
					"spriteSourceSize": {
						"x": 0,
						"y": 0,
						"w": 92,
						"h": 43
					},
					"frame": {
						"x": 1,
						"y": 1,
						"w": 92,
						"h": 43
					}
				},
				{
					"filename": "6",
					"rotated": false,
					"trimmed": false,
					"sourceSize": {
						"w": 92,
						"h": 43
					},
					"spriteSourceSize": {
						"x": 0,
						"y": 0,
						"w": 92,
						"h": 43
					},
					"frame": {
						"x": 95,
						"y": 1,
						"w": 92,
						"h": 43
					}
				},
				{
					"filename": "7",
					"rotated": false,
					"trimmed": false,
					"sourceSize": {
						"w": 92,
						"h": 43
					},
					"spriteSourceSize": {
						"x": 0,
						"y": 0,
						"w": 92,
						"h": 43
					},
					"frame": {
						"x": 189,
						"y": 1,
						"w": 92,
						"h": 43
					}
				}
			]
		}
	],
	"meta": {
		"app": "https://www.codeandweb.com/texturepacker",
		"version": "3.0",
		"smartupdate": "$TexturePacker:SmartUpdate:d31eafb99af39a6c828088a6e255e807:a165d85377c5b659eaa2213c242caea6:1010675b1f2726343f17fea9ec822b82$"
	}
}
