{
	"textures": [
		{
			"image": "18.png",
			"format": "RGBA8888",
			"size": {
				"w": 742,
				"h": 119
			},
			"scale": 1,
			"frames": [
				{
					"filename": "1",
					"rotated": false,
					"trimmed": false,
					"sourceSize": {
						"w": 104,
						"h": 117
					},
					"spriteSourceSize": {
						"x": 0,
						"y": 0,
						"w": 104,
						"h": 117
					},
					"frame": {
						"x": 1,
						"y": 1,
						"w": 104,
						"h": 117
					}
				},
				{
					"filename": "10",
					"rotated": false,
					"trimmed": false,
					"sourceSize": {
						"w": 104,
						"h": 117
					},
					"spriteSourceSize": {
						"x": 0,
						"y": 0,
						"w": 104,
						"h": 117
					},
					"frame": {
						"x": 107,
						"y": 1,
						"w": 104,
						"h": 117
					}
				},
				{
					"filename": "11",
					"rotated": false,
					"trimmed": false,
					"sourceSize": {
						"w": 104,
						"h": 117
					},
					"spriteSourceSize": {
						"x": 0,
						"y": 0,
						"w": 104,
						"h": 117
					},
					"frame": {
						"x": 213,
						"y": 1,
						"w": 104,
						"h": 117
					}
				},
				{
					"filename": "12",
					"rotated": false,
					"trimmed": false,
					"sourceSize": {
						"w": 104,
						"h": 117
					},
					"spriteSourceSize": {
						"x": 0,
						"y": 0,
						"w": 104,
						"h": 117
					},
					"frame": {
						"x": 319,
						"y": 1,
						"w": 104,
						"h": 117
					}
				},
				{
					"filename": "13",
					"rotated": false,
					"trimmed": false,
					"sourceSize": {
						"w": 104,
						"h": 117
					},
					"spriteSourceSize": {
						"x": 0,
						"y": 0,
						"w": 104,
						"h": 117
					},
					"frame": {
						"x": 425,
						"y": 1,
						"w": 104,
						"h": 117
					}
				},
				{
					"filename": "14",
					"rotated": false,
					"trimmed": false,
					"sourceSize": {
						"w": 104,
						"h": 117
					},
					"spriteSourceSize": {
						"x": 0,
						"y": 0,
						"w": 104,
						"h": 117
					},
					"frame": {
						"x": 531,
						"y": 1,
						"w": 104,
						"h": 117
					}
				},
				{
					"filename": "2",
					"rotated": false,
					"trimmed": false,
					"sourceSize": {
						"w": 104,
						"h": 117
					},
					"spriteSourceSize": {
						"x": 0,
						"y": 0,
						"w": 104,
						"h": 117
					},
					"frame": {
						"x": 637,
						"y": 1,
						"w": 104,
						"h": 117
					}
				},
				{
					"filename": "3",
					"rotated": false,
					"trimmed": false,
					"sourceSize": {
						"w": 104,
						"h": 117
					},
					"spriteSourceSize": {
						"x": 0,
						"y": 0,
						"w": 104,
						"h": 117
					},
					"frame": {
						"x": 637,
						"y": 1,
						"w": 104,
						"h": 117
					}
				},
				{
					"filename": "4",
					"rotated": false,
					"trimmed": false,
					"sourceSize": {
						"w": 104,
						"h": 117
					},
					"spriteSourceSize": {
						"x": 0,
						"y": 0,
						"w": 104,
						"h": 117
					},
					"frame": {
						"x": 637,
						"y": 1,
						"w": 104,
						"h": 117
					}
				},
				{
					"filename": "5",
					"rotated": false,
					"trimmed": false,
					"sourceSize": {
						"w": 104,
						"h": 117
					},
					"spriteSourceSize": {
						"x": 0,
						"y": 0,
						"w": 104,
						"h": 117
					},
					"frame": {
						"x": 637,
						"y": 1,
						"w": 104,
						"h": 117
					}
				},
				{
					"filename": "6",
					"rotated": false,
					"trimmed": false,
					"sourceSize": {
						"w": 104,
						"h": 117
					},
					"spriteSourceSize": {
						"x": 0,
						"y": 0,
						"w": 104,
						"h": 117
					},
					"frame": {
						"x": 637,
						"y": 1,
						"w": 104,
						"h": 117
					}
				},
				{
					"filename": "7",
					"rotated": false,
					"trimmed": false,
					"sourceSize": {
						"w": 104,
						"h": 117
					},
					"spriteSourceSize": {
						"x": 0,
						"y": 0,
						"w": 104,
						"h": 117
					},
					"frame": {
						"x": 637,
						"y": 1,
						"w": 104,
						"h": 117
					}
				},
				{
					"filename": "8",
					"rotated": false,
					"trimmed": false,
					"sourceSize": {
						"w": 104,
						"h": 117
					},
					"spriteSourceSize": {
						"x": 0,
						"y": 0,
						"w": 104,
						"h": 117
					},
					"frame": {
						"x": 637,
						"y": 1,
						"w": 104,
						"h": 117
					}
				},
				{
					"filename": "9",
					"rotated": false,
					"trimmed": false,
					"sourceSize": {
						"w": 104,
						"h": 117
					},
					"spriteSourceSize": {
						"x": 0,
						"y": 0,
						"w": 104,
						"h": 117
					},
					"frame": {
						"x": 637,
						"y": 1,
						"w": 104,
						"h": 117
					}
				}
			]
		}
	],
	"meta": {
		"app": "https://www.codeandweb.com/texturepacker",
		"version": "3.0",
		"smartupdate": "$TexturePacker:SmartUpdate:6f0e09f7cdc99147c2ccecef62780a63:1b161cffc1529a364a37aac1f701a3dc:e4edd64e1d3b532c039a4eea1103716a$"
	}
}
