{
	"textures": [
		{
			"image": "11.png",
			"format": "RGBA8888",
			"size": {
				"w": 1912,
				"h": 322
			},
			"scale": 1,
			"frames": [
				{
					"filename": "1",
					"rotated": false,
					"trimmed": false,
					"sourceSize": {
						"w": 237,
						"h": 320
					},
					"spriteSourceSize": {
						"x": 0,
						"y": 0,
						"w": 237,
						"h": 320
					},
					"frame": {
						"x": 1,
						"y": 1,
						"w": 237,
						"h": 320
					}
				},
				{
					"filename": "10",
					"rotated": false,
					"trimmed": false,
					"sourceSize": {
						"w": 237,
						"h": 320
					},
					"spriteSourceSize": {
						"x": 0,
						"y": 0,
						"w": 237,
						"h": 320
					},
					"frame": {
						"x": 240,
						"y": 1,
						"w": 237,
						"h": 320
					}
				},
				{
					"filename": "11",
					"rotated": false,
					"trimmed": false,
					"sourceSize": {
						"w": 237,
						"h": 320
					},
					"spriteSourceSize": {
						"x": 0,
						"y": 0,
						"w": 237,
						"h": 320
					},
					"frame": {
						"x": 240,
						"y": 1,
						"w": 237,
						"h": 320
					}
				},
				{
					"filename": "12",
					"rotated": false,
					"trimmed": false,
					"sourceSize": {
						"w": 237,
						"h": 320
					},
					"spriteSourceSize": {
						"x": 0,
						"y": 0,
						"w": 237,
						"h": 320
					},
					"frame": {
						"x": 479,
						"y": 1,
						"w": 237,
						"h": 320
					}
				},
				{
					"filename": "13",
					"rotated": false,
					"trimmed": false,
					"sourceSize": {
						"w": 237,
						"h": 320
					},
					"spriteSourceSize": {
						"x": 0,
						"y": 0,
						"w": 237,
						"h": 320
					},
					"frame": {
						"x": 718,
						"y": 1,
						"w": 237,
						"h": 320
					}
				},
				{
					"filename": "2",
					"rotated": false,
					"trimmed": false,
					"sourceSize": {
						"w": 237,
						"h": 320
					},
					"spriteSourceSize": {
						"x": 0,
						"y": 0,
						"w": 237,
						"h": 320
					},
					"frame": {
						"x": 957,
						"y": 1,
						"w": 237,
						"h": 320
					}
				},
				{
					"filename": "3",
					"rotated": false,
					"trimmed": false,
					"sourceSize": {
						"w": 237,
						"h": 320
					},
					"spriteSourceSize": {
						"x": 0,
						"y": 0,
						"w": 237,
						"h": 320
					},
					"frame": {
						"x": 1196,
						"y": 1,
						"w": 237,
						"h": 320
					}
				},
				{
					"filename": "4",
					"rotated": false,
					"trimmed": false,
					"sourceSize": {
						"w": 237,
						"h": 320
					},
					"spriteSourceSize": {
						"x": 0,
						"y": 0,
						"w": 237,
						"h": 320
					},
					"frame": {
						"x": 1435,
						"y": 1,
						"w": 237,
						"h": 320
					}
				},
				{
					"filename": "5",
					"rotated": false,
					"trimmed": false,
					"sourceSize": {
						"w": 237,
						"h": 320
					},
					"spriteSourceSize": {
						"x": 0,
						"y": 0,
						"w": 237,
						"h": 320
					},
					"frame": {
						"x": 1674,
						"y": 1,
						"w": 237,
						"h": 320
					}
				},
				{
					"filename": "6",
					"rotated": false,
					"trimmed": false,
					"sourceSize": {
						"w": 237,
						"h": 320
					},
					"spriteSourceSize": {
						"x": 0,
						"y": 0,
						"w": 237,
						"h": 320
					},
					"frame": {
						"x": 1674,
						"y": 1,
						"w": 237,
						"h": 320
					}
				},
				{
					"filename": "7",
					"rotated": false,
					"trimmed": false,
					"sourceSize": {
						"w": 237,
						"h": 320
					},
					"spriteSourceSize": {
						"x": 0,
						"y": 0,
						"w": 237,
						"h": 320
					},
					"frame": {
						"x": 1674,
						"y": 1,
						"w": 237,
						"h": 320
					}
				},
				{
					"filename": "8",
					"rotated": false,
					"trimmed": false,
					"sourceSize": {
						"w": 237,
						"h": 320
					},
					"spriteSourceSize": {
						"x": 0,
						"y": 0,
						"w": 237,
						"h": 320
					},
					"frame": {
						"x": 1674,
						"y": 1,
						"w": 237,
						"h": 320
					}
				},
				{
					"filename": "9",
					"rotated": false,
					"trimmed": false,
					"sourceSize": {
						"w": 237,
						"h": 320
					},
					"spriteSourceSize": {
						"x": 0,
						"y": 0,
						"w": 237,
						"h": 320
					},
					"frame": {
						"x": 1674,
						"y": 1,
						"w": 237,
						"h": 320
					}
				}
			]
		}
	],
	"meta": {
		"app": "https://www.codeandweb.com/texturepacker",
		"version": "3.0",
		"smartupdate": "$TexturePacker:SmartUpdate:05f2a47a0c17202f5b8ab63a092ead28:e7a170cebc14cf1ddf632d6e6e4580f2:aaee697773d245ec0ff66c8d6aa83826$"
	}
}
